envcfglib/__init__.py
envcfglib/config.py
envcfglib-0.1.6.dist-info/METADATA
envcfglib-0.1.6.dist-info/WHEEL
envcfglib-0.1.6.dist-info/licenses/LICENSE
envcfglib-0.1.6.dist-info/RECORD
